README
setup.cfg
setup.py
izaber_flask_wamp/__init__.py
izaber_flask_wamp/app.py
izaber_flask_wamp/authenticators.py
izaber_flask_wamp/authorizers.py
izaber_flask_wamp/client.py
izaber_flask_wamp/common.py
izaber_flask_wamp/registrations.py
izaber_flask_wamp/uri.py
izaber_flask_wamp/wamp.py
izaber_flask_wamp.egg-info/PKG-INFO
izaber_flask_wamp.egg-info/SOURCES.txt
izaber_flask_wamp.egg-info/dependency_links.txt
izaber_flask_wamp.egg-info/not-zip-safe
izaber_flask_wamp.egg-info/requires.txt
izaber_flask_wamp.egg-info/top_level.txt