Metadata-Version: 1.1
Name: izaber-flask-wamp
Version: 1.20180929
Summary: Base load point for iZaber WAMP services through Flask
Home-page: https://github.com/zabertech/izaber-flask-wamp
Author: Aki Mimoto
Author-email: aki+izaber@zaber.com
License: MIT
Download-URL: https://github.com/zabertech/izaber-flask-wamp/archive/1.20180929.tar.gz
Platform: UNKNOWN
